hydrotools/caches/__init__.py
hydrotools/caches/_version.py
hydrotools/caches/hdf.py
hydrotools.caches-0.1.5.dist-info/LICENSE
hydrotools.caches-0.1.5.dist-info/METADATA
hydrotools.caches-0.1.5.dist-info/WHEEL
hydrotools.caches-0.1.5.dist-info/top_level.txt
hydrotools.caches-0.1.5.dist-info/RECORD
