Metadata-Version: 2.1
Name: hydrotools.caches
Version: 0.1.5
Summary: Variety of object caching utilities for OWPHydroTools.
Author-email: "Jason A. Regina" <jason.regina@noaa.gov>
License: “Software code created by U.S. Government employees is not subject to copyright
Project-URL: Homepage, https://github.com/NOAA-OWP/hydrotools
Project-URL: Documentation, https://noaa-owp.github.io/hydrotools/hydrotools.caches.html
Project-URL: Repository, https://github.com/NOAA-OWP/hydrotools/tree/main/python/caches
Project-URL: Bug Tracker, https://github.com/NOAA-OWP/hydrotools/issues
Classifier: Development Status :: 5 - Production/Stable
Classifier: Intended Audience :: Education
Classifier: Intended Audience :: Science/Research
Classifier: License :: Free To Use But Restricted
Classifier: Programming Language :: Python :: 3.8
Classifier: Programming Language :: Python :: 3.9
Classifier: Programming Language :: Python :: 3.10
Classifier: Programming Language :: Python :: 3.11
Classifier: Topic :: Scientific/Engineering :: Hydrology
Classifier: Operating System :: OS Independent
Requires-Python: >=3.8
License-File: LICENSE
Requires-Dist: numpy<2; python_version < "3.10"
Requires-Dist: pandas
Requires-Dist: tables
Provides-Extra: develop
Requires-Dist: pytest; extra == "develop"
